am_algorithms/__init__.py
am_algorithms/app.py
am_algorithms/geometry/__init__.py
am_algorithms/geometry/point.py
am_algorithms/geometry/triangle.py
am_algorithms/number/__init__.py
am_algorithms/number/bisection.py
am_algorithms/number/fib.py
am_algorithms/number/find_min_element.py
am_algorithms/number/gcd.py
am_algorithms/number/horner.py
am_algorithms/number/numerical_integration.py
am_algorithms/number/sort.py
am_algorithms/number/utils.py
am_algorithms/sort_generic.py
am_algorithms/text/__init__.py
am_algorithms/text/cipher.py
am_algorithms/text/utils.py
am_algorithms-0.1.0.dist-info/entry_points.txt
am_algorithms-0.1.0.dist-info/METADATA
am_algorithms-0.1.0.dist-info/WHEEL
am_algorithms-0.1.0.dist-info/RECORD
